{
  "type": "doc",
  "content": [
    {
      "type": "heading",
      "attrs": {
        "level": 1
      },
      "content": [
        {
          "type": "text",
          "text": "Wahrnehmungsstörungen"
        }
      ]
    },
    {
      "type": "paragraph",
      "content": [
        {
          "type": "text",
          "text": "Patienten berichten eher nicht spontan über halluzinatorische Erlebnisse, aus Furcht, als “verrückt” bezeichnet zu werden."
        }
      ]
    },
    {
      "type": "paragraph",
      "content": [
        {
          "type": "text",
          "text": "Anzeichen können sein: Fixierung eines bestimmten Punktes im Zimmer, plötzliche Handbewegungen."
        }
      ]
    },
    {
      "type": "paragraph",
      "content": [
        {
          "type": "text",
          "text": "Einstiegsfragen"
        }
      ]
    },
    {
      "type": "bulletList",
      "content": [
        {
          "type": "listItem",
          "content": [
            {
              "type": "paragraph",
              "content": [
                {
                  "type": "text",
                  "text": "Gibt es etwas, das Sie ablenkt oder ängstigt?"
                }
              ]
            }
          ]
        },
        {
          "type": "listItem",
          "content": [
            {
              "type": "paragraph",
              "content": [
                {
                  "type": "text",
                  "text": "Hören Sie Stimmen?"
                }
              ]
            }
          ]
        },
        {
          "type": "listItem",
          "content": [
            {
              "type": "paragraph",
              "content": [
                {
                  "type": "text",
                  "text": "Sind es vielleicht nur Ihre Gedanken, die da laut werden?"
                }
              ]
            }
          ]
        },
        {
          "type": "listItem",
          "content": [
            {
              "type": "paragraph",
              "content": [
                {
                  "type": "text",
                  "text": "Haben Sie Personen oder Gegenstände gesehen, die andere nicht sehen können?"
                }
              ]
            }
          ]
        },
        {
          "type": "listItem",
          "content": [
            {
              "type": "paragraph",
              "content": [
                {
                  "type": "text",
                  "text": "Gehen in Ihrem Körper merkwürdige Dinge vor?"
                }
              ]
            }
          ]
        },
        {
          "type": "listItem",
          "content": [
            {
              "type": "paragraph",
              "content": [
                {
                  "type": "text",
                  "text": "Haben Sie noch andere eigenartige Wahrnehmungen?"
                }
              ]
            }
          ]
        }
      ]
    },
    {
      "type": "heading",
      "attrs": {
        "level": 2
      },
      "content": [
        {
          "type": "text",
          "text": "Halluzination (Trugwahrnehmung)"
        }
      ]
    },
    {
      "type": "bulletList",
      "content": [
        {
          "type": "listItem",
          "content": [
            {
              "type": "paragraph",
              "content": [
                {
                  "type": "text",
                  "text": "Wahrnehmungserlebnisse ohne entsprechenden Außenreiz, "
                }
              ]
            }
          ]
        },
        {
          "type": "listItem",
          "content": [
            {
              "type": "paragraph",
              "content": [
                {
                  "type": "text",
                  "text": "Werden für wirkliche Sinneseindrücke gehalten"
                }
              ]
            }
          ]
        },
        {
          "type": "listItem",
          "content": [
            {
              "type": "paragraph",
              "content": [
                {
                  "type": "text",
                  "text": "Kann auf allen Sinnesgebieten auftreten; am häufigsten auditiv + visuell"
                }
              ]
            }
          ]
        },
        {
          "type": "listItem",
          "content": [
            {
              "type": "paragraph",
              "content": [
                {
                  "type": "text",
                  "text": "Bei Schizophrenie fast immer mit Wahn verknüpft"
                }
              ]
            }
          ]
        },
        {
          "type": "listItem",
          "content": [
            {
              "type": "paragraph",
              "content": [
                {
                  "type": "text",
                  "text": "Bei organischen Psychosen nicht unbedingt mit Wahn"
                }
              ]
            }
          ]
        }
      ]
    },
    {
      "type": "heading",
      "attrs": {
        "level": 3
      },
      "content": [
        {
          "type": "text",
          "text": "Akustische Halluzinationen"
        }
      ]
    },
    {
      "type": "bulletList",
      "content": [
        {
          "type": "listItem",
          "content": [
            {
              "type": "paragraph",
              "content": [
                {
                  "type": "text",
                  "text": "Akoasmen: Unstrukturierte, einfache (nonverbale) Geräuschhalluzinationen aller Art"
                }
              ]
            }
          ]
        },
        {
          "type": "listItem",
          "content": [
            {
              "type": "paragraph",
              "content": [
                {
                  "type": "text",
                  "text": "Stimmenhören"
                }
              ]
            }
          ]
        },
        {
          "type": "listItem",
          "content": [
            {
              "type": "paragraph",
              "content": [
                {
                  "type": "text",
                  "text": "Imperative Stimmen, die den Patienten zu einer Handlung auffordern (z.B. einen Suizid zu begehen)."
                }
              ]
            }
          ]
        },
        {
          "type": "listItem",
          "content": [
            {
              "type": "paragraph",
              "content": [
                {
                  "type": "text",
                  "text": "Kommentierende Stimmen, die das Handeln des Patienten kommentieren, nicht selten abschätzig"
                }
              ]
            }
          ]
        },
        {
          "type": "listItem",
          "content": [
            {
              "type": "paragraph",
              "content": [
                {
                  "type": "text",
                  "text": "Dialogische Stimmen, die sich miteinander Unterhalten, meistens über den Betreffenden"
                }
              ]
            }
          ]
        }
      ]
    },
    {
      "type": "paragraph",
      "content": [
        {
          "type": "text",
          "text": "Bei"
        }
      ]
    },
    {
      "type": "bulletList",
      "content": [
        {
          "type": "listItem",
          "content": [
            {
              "type": "paragraph",
              "content": [
                {
                  "type": "text",
                  "text": "Paranoider Schizophrenie"
                }
              ]
            }
          ]
        }
      ]
    },
    {
      "type": "paragraph",
      "content": [
        {
          "type": "text",
          "text": "und organische Psychosen:"
        }
      ]
    },
    {
      "type": "bulletList",
      "content": [
        {
          "type": "listItem",
          "content": [
            {
              "type": "paragraph",
              "content": [
                {
                  "type": "text",
                  "text": "Alkoholhalluzinose"
                }
              ]
            }
          ]
        },
        {
          "type": "listItem",
          "content": [
            {
              "type": "paragraph",
              "content": [
                {
                  "type": "text",
                  "text": "Alkoholenzugsdelier"
                }
              ]
            }
          ]
        },
        {
          "type": "listItem",
          "content": [
            {
              "type": "paragraph",
              "content": [
                {
                  "type": "text",
                  "text": "Eliptische Aura"
                }
              ]
            }
          ]
        },
        {
          "type": "listItem",
          "content": [
            {
              "type": "paragraph",
              "content": [
                {
                  "type": "text",
                  "text": "Wahnhafte Störungen"
                }
              ]
            }
          ]
        },
        {
          "type": "listItem",
          "content": [
            {
              "type": "paragraph",
              "content": [
                {
                  "type": "text",
                  "text": "Schizoaffektive Störungen"
                }
              ]
            }
          ]
        }
      ]
    },
    {
      "type": "heading",
      "attrs": {
        "level": 3
      },
      "content": [
        {
          "type": "text",
          "text": "Optische Halluzinationen"
        }
      ]
    },
    {
      "type": "bulletList",
      "content": [
        {
          "type": "listItem",
          "content": [
            {
              "type": "paragraph",
              "content": [
                {
                  "type": "text",
                  "text": "Wahrnehmung von Objekten und/oder Person, die nicht vorhanden sind"
                }
              ]
            }
          ]
        },
        {
          "type": "listItem",
          "content": [
            {
              "type": "paragraph",
              "content": [
                {
                  "type": "text",
                  "text": "Photopsien: einfache optischen Trugwahrnehmungen (Funken, Flecken, Muster, etc.)"
                }
              ]
            }
          ]
        },
        {
          "type": "listItem",
          "content": [
            {
              "type": "paragraph",
              "content": [
                {
                  "type": "text",
                  "text": "Szenisch:  “weiße Mäuse” etc."
                }
              ]
            }
          ]
        }
      ]
    },
    {
      "type": "paragraph",
      "content": [
        {
          "type": "text",
          "text": "Bei"
        }
      ]
    },
    {
      "type": "bulletList",
      "content": [
        {
          "type": "listItem",
          "content": [
            {
              "type": "paragraph",
              "content": [
                {
                  "type": "text",
                  "text": "Exiskkose (Dehydration)"
                }
              ]
            }
          ]
        }
      ]
    },
    {
      "type": "bulletList",
      "content": [
        {
          "type": "listItem",
          "content": [
            {
              "type": "paragraph",
              "content": [
                {
                  "type": "text",
                  "text": "Alkoholenzugsdelier"
                }
              ]
            }
          ]
        },
        {
          "type": "listItem",
          "content": [
            {
              "type": "paragraph",
              "content": [
                {
                  "type": "text",
                  "text": "LSD-Psychose"
                }
              ]
            }
          ]
        },
        {
          "type": "listItem",
          "content": [
            {
              "type": "paragraph",
              "content": [
                {
                  "type": "text",
                  "text": "Läsionen des Okzipitallappens (Sehzentrum)"
                }
              ]
            }
          ]
        }
      ]
    },
    {
      "type": "heading",
      "attrs": {
        "level": 3
      },
      "content": [
        {
          "type": "text",
          "text": "Olfaktorische und gustatorische Halluzinationen"
        }
      ]
    },
    {
      "type": "paragraph",
      "content": [
        {
          "type": "text",
          "text": "Bei"
        }
      ]
    },
    {
      "type": "bulletList",
      "content": [
        {
          "type": "listItem",
          "content": [
            {
              "type": "paragraph",
              "content": [
                {
                  "type": "text",
                  "text": "Schizophrenien mit wahnhaften Verfolgungs- und Vergiftungsängsten (z.B. Gasgeruch) - synthym"
                }
              ]
            }
          ]
        },
        {
          "type": "listItem",
          "content": [
            {
              "type": "paragraph",
              "content": [
                {
                  "type": "text",
                  "text": "Psychotische Depression, z.B. Fäulnis-, Leichen-, Verwesungsgeruch - synthym"
                }
              ]
            }
          ]
        },
        {
          "type": "listItem",
          "content": [
            {
              "type": "paragraph",
              "content": [
                {
                  "type": "text",
                  "text": "Tumor"
                }
              ]
            }
          ]
        },
        {
          "type": "listItem",
          "content": [
            {
              "type": "paragraph",
              "content": [
                {
                  "type": "text",
                  "text": "Epileptische Anfälle"
                }
              ]
            }
          ]
        }
      ]
    },
    {
      "type": "heading",
      "attrs": {
        "level": 3
      },
      "content": [
        {
          "type": "text",
          "text": "Taktische (haptische) Halluzinationen"
        }
      ]
    },
    {
      "type": "bulletList",
      "content": [
        {
          "type": "listItem",
          "content": [
            {
              "type": "paragraph",
              "content": [
                {
                  "type": "text",
                  "text": "Patient hat das Gefühl berührt/angefasst zu werden"
                }
              ]
            }
          ]
        },
        {
          "type": "listItem",
          "content": [
            {
              "type": "paragraph",
              "content": [
                {
                  "type": "text",
                  "text": "Druck im Nacken, Einstechen, sexuelle Berührungen"
                }
              ]
            }
          ]
        },
        {
          "type": "listItem",
          "content": [
            {
              "type": "paragraph",
              "content": [
                {
                  "type": "text",
                  "text": "Andere, unspezifische Hautempfindungen"
                }
              ]
            }
          ]
        }
      ]
    },
    {
      "type": "paragraph",
      "content": [
        {
          "type": "text",
          "text": "Bei"
        }
      ]
    },
    {
      "type": "bulletList",
      "content": [
        {
          "type": "listItem",
          "content": [
            {
              "type": "paragraph",
              "content": [
                {
                  "type": "text",
                  "text": "V.a. ältere Patienten mit organischer Psychose"
                }
              ]
            }
          ]
        },
        {
          "type": "listItem",
          "content": [
            {
              "type": "paragraph",
              "content": [
                {
                  "type": "text",
                  "text": "Alkoholenzugsdelier"
                }
              ]
            }
          ]
        },
        {
          "type": "listItem",
          "content": [
            {
              "type": "paragraph",
              "content": [
                {
                  "type": "text",
                  "text": "Kokaindelierium"
                }
              ]
            }
          ]
        },
        {
          "type": "listItem",
          "content": [
            {
              "type": "paragraph",
              "content": [
                {
                  "type": "text",
                  "text": "Schizophrenie/Depression (seltener)"
                }
              ]
            }
          ]
        }
      ]
    },
    {
      "type": "paragraph",
      "content": [
        {
          "type": "text",
          "text": "Sonderform: Chronisch taktile Halluzinose - Überzeugung Insekten leben in der Haut."
        }
      ]
    },
    {
      "type": "heading",
      "attrs": {
        "level": 3
      },
      "content": [
        {
          "type": "text",
          "text": "Zönästhesien"
        }
      ]
    },
    {
      "type": "bulletList",
      "content": [
        {
          "type": "listItem",
          "content": [
            {
              "type": "paragraph",
              "content": [
                {
                  "type": "text",
                  "text": "Bizarre Leibempfindungen"
                }
              ]
            }
          ]
        },
        {
          "type": "listItem",
          "content": [
            {
              "type": "paragraph",
              "content": [
                {
                  "type": "text",
                  "text": "Inneres Verfaulen, Feuer im Körper, Gehirn schwappt im Kopf hin-und-her"
                }
              ]
            }
          ]
        },
        {
          "type": "listItem",
          "content": [
            {
              "type": "paragraph",
              "content": [
                {
                  "type": "text",
                  "text": "Wird nicht als “von außen gemacht” erlebt wie bei Ich-Störung"
                }
              ]
            }
          ]
        }
      ]
    },
    {
      "type": "paragraph",
      "content": [
        {
          "type": "text",
          "text": "Bei "
        }
      ]
    },
    {
      "type": "bulletList",
      "content": [
        {
          "type": "listItem",
          "content": [
            {
              "type": "paragraph",
              "content": [
                {
                  "type": "text",
                  "text": "OPS"
                }
              ]
            }
          ]
        },
        {
          "type": "listItem",
          "content": [
            {
              "type": "paragraph",
              "content": [
                {
                  "type": "text",
                  "text": "Hypochondrische Störungen"
                }
              ]
            }
          ]
        }
      ]
    },
    {
      "type": "heading",
      "attrs": {
        "level": 3
      },
      "content": [
        {
          "type": "text",
          "text": "Leibhalluzinationen (zönästische Halluzinationen)"
        }
      ]
    },
    {
      "type": "bulletList",
      "content": [
        {
          "type": "listItem",
          "content": [
            {
              "type": "paragraph",
              "content": [
                {
                  "type": "text",
                  "text": "Missempfindungen"
                }
              ]
            }
          ]
        },
        {
          "type": "listItem",
          "content": [
            {
              "type": "paragraph",
              "content": [
                {
                  "type": "text",
                  "text": "Schmerzen"
                }
              ]
            }
          ]
        },
        {
          "type": "listItem",
          "content": [
            {
              "type": "paragraph",
              "content": [
                {
                  "type": "text",
                  "text": "Also von außen gemacht erlebt"
                }
              ]
            }
          ]
        },
        {
          "type": "listItem",
          "content": [
            {
              "type": "paragraph",
              "content": [
                {
                  "type": "text",
                  "text": "Ich wurde Hypnotisiert / Magnetisiert"
                }
              ]
            }
          ]
        }
      ]
    },
    {
      "type": "heading",
      "attrs": {
        "level": 2
      },
      "content": [
        {
          "type": "text",
          "text": "Halluzinationen nahestehende Phänomene"
        }
      ]
    },
    {
      "type": "heading",
      "attrs": {
        "level": 3
      },
      "content": [
        {
          "type": "text",
          "text": "Pseudohalluzinationen"
        }
      ]
    },
    {
      "type": "bulletList",
      "content": [
        {
          "type": "listItem",
          "content": [
            {
              "type": "paragraph",
              "content": [
                {
                  "type": "text",
                  "text": "Patient erkennet, dass seine Halluzinationen irreal sind"
                }
              ]
            }
          ]
        },
        {
          "type": "listItem",
          "content": [
            {
              "type": "paragraph",
              "content": [
                {
                  "type": "text",
                  "text": "Selten, kommt fast nur auf akustischem und visuellem Gebiet vor"
                }
              ]
            }
          ]
        },
        {
          "type": "listItem",
          "content": [
            {
              "type": "paragraph",
              "content": [
                {
                  "type": "text",
                  "text": "Z.B. Hypnagoge Halluzination im Halbschlaf, schwere Ermüdung, Fieber, Drogen, etc."
                }
              ]
            }
          ]
        }
      ]
    },
    {
      "type": "heading",
      "attrs": {
        "level": 3
      },
      "content": [
        {
          "type": "text",
          "text": "Illusion (illusionäre Verkennung)"
        }
      ]
    },
    {
      "type": "bulletList",
      "content": [
        {
          "type": "listItem",
          "content": [
            {
              "type": "paragraph",
              "content": [
                {
                  "type": "text",
                  "text": "“Der Räuber im Busch” (Busch wird nicht gesehen)"
                }
              ]
            }
          ]
        },
        {
          "type": "listItem",
          "content": [
            {
              "type": "paragraph",
              "content": [
                {
                  "type": "text",
                  "text": "Missdeutung von Sinneseindrücken"
                }
              ]
            }
          ]
        },
        {
          "type": "listItem",
          "content": [
            {
              "type": "paragraph",
              "content": [
                {
                  "type": "text",
                  "text": "Etwas real vorhandenes wird für etwas anderes gehalten"
                }
              ]
            }
          ]
        },
        {
          "type": "listItem",
          "content": [
            {
              "type": "paragraph",
              "content": [
                {
                  "type": "text",
                  "text": "Tritt auch im normalpsychischen Bereich auf, z.B. bei Kindern, Übermüdung, Fieber, Drogen, affektiver Anspannung"
                }
              ]
            }
          ]
        },
        {
          "type": "listItem",
          "content": [
            {
              "type": "paragraph",
              "content": [
                {
                  "type": "text",
                  "text": "DD: Im Wahn wird der Gegenstand richtig erkannt, aber wahnhaft umgedeutet."
                }
              ]
            }
          ]
        }
      ]
    },
    {
      "type": "heading",
      "attrs": {
        "level": 3
      },
      "content": [
        {
          "type": "text",
          "text": "Pareidolien"
        }
      ]
    },
    {
      "type": "bulletList",
      "content": [
        {
          "type": "listItem",
          "content": [
            {
              "type": "paragraph",
              "content": [
                {
                  "type": "text",
                  "text": "Busch + Gestalt (beides wird gesehen)"
                }
              ]
            }
          ]
        },
        {
          "type": "listItem",
          "content": [
            {
              "type": "paragraph",
              "content": [
                {
                  "type": "text",
                  "text": "Man sieht die Wolken und Gesichter darin"
                }
              ]
            }
          ]
        },
        {
          "type": "listItem",
          "content": [
            {
              "type": "paragraph",
              "content": [
                {
                  "type": "text",
                  "text": "Wort in das Rauschen des Waldes"
                }
              ]
            }
          ]
        },
        {
          "type": "listItem",
          "content": [
            {
              "type": "paragraph",
              "content": [
                {
                  "type": "text",
                  "text": "Neben dem wirklichen Objekt werden weitere Inhalte hineingesehen"
                }
              ]
            }
          ]
        }
      ]
    },
    {
      "type": "paragraph",
      "content": [
        {
          "type": "text",
          "text": "Bei"
        }
      ]
    },
    {
      "type": "bulletList",
      "content": [
        {
          "type": "listItem",
          "content": [
            {
              "type": "paragraph",
              "content": [
                {
                  "type": "text",
                  "text": "Gesunden"
                }
              ]
            }
          ]
        },
        {
          "type": "listItem",
          "content": [
            {
              "type": "paragraph",
              "content": [
                {
                  "type": "text",
                  "text": "Fieber"
                }
              ]
            }
          ]
        },
        {
          "type": "listItem",
          "content": [
            {
              "type": "paragraph",
              "content": [
                {
                  "type": "text",
                  "text": "Panikstörungen"
                }
              ]
            }
          ]
        },
        {
          "type": "listItem",
          "content": [
            {
              "type": "paragraph",
              "content": [
                {
                  "type": "text",
                  "text": "Starker Übermüdung"
                }
              ]
            }
          ]
        },
        {
          "type": "listItem",
          "content": [
            {
              "type": "paragraph",
              "content": [
                {
                  "type": "text",
                  "text": "Psychischer Belastung"
                }
              ]
            }
          ]
        },
        {
          "type": "listItem",
          "content": [
            {
              "type": "paragraph",
              "content": [
                {
                  "type": "text",
                  "text": "Drogenmissbrauch"
                }
              ]
            }
          ]
        },
        {
          "type": "listItem",
          "content": [
            {
              "type": "paragraph",
              "content": [
                {
                  "type": "text",
                  "text": "Alkoholintoxikation"
                }
              ]
            }
          ]
        },
        {
          "type": "listItem",
          "content": [
            {
              "type": "paragraph",
              "content": [
                {
                  "type": "text",
                  "text": "Prä-Delir"
                }
              ]
            }
          ]
        }
      ]
    },
    {
      "type": "heading",
      "attrs": {
        "level": 2
      },
      "content": [
        {
          "type": "text",
          "text": "Einfache Wahrnehmungsveränderungen"
        }
      ]
    },
    {
      "type": "heading",
      "attrs": {
        "level": 3
      },
      "content": [
        {
          "type": "text",
          "text": "Veränderung der Wahrnehmungsintensität"
        }
      ]
    },
    {
      "type": "bulletList",
      "content": [
        {
          "type": "listItem",
          "content": [
            {
              "type": "paragraph",
              "content": [
                {
                  "type": "text",
                  "text": "Sinneseindrücke mehr/weniger intensiv, farbig, scharf etc."
                }
              ]
            }
          ]
        }
      ]
    },
    {
      "type": "paragraph",
      "content": [
        {
          "type": "text",
          "text": "Bei"
        }
      ]
    },
    {
      "type": "bulletList",
      "content": [
        {
          "type": "listItem",
          "content": [
            {
              "type": "paragraph",
              "content": [
                {
                  "type": "text",
                  "text": "Augenerkrankungen"
                }
              ]
            }
          ]
        },
        {
          "type": "listItem",
          "content": [
            {
              "type": "paragraph",
              "content": [
                {
                  "type": "text",
                  "text": "Entzündliche Veränderungen im Sehzentrum"
                }
              ]
            }
          ]
        },
        {
          "type": "listItem",
          "content": [
            {
              "type": "paragraph",
              "content": [
                {
                  "type": "text",
                  "text": "Depersonalisation "
                }
              ]
            }
          ]
        }
      ]
    },
    {
      "type": "paragraph",
      "content": [
        {
          "type": "text",
          "text": "OPS"
        }
      ]
    },
    {
      "type": "bulletList",
      "content": [
        {
          "type": "listItem",
          "content": [
            {
              "type": "paragraph",
              "content": [
                {
                  "type": "text",
                  "text": "Schlaganfälle"
                }
              ]
            }
          ]
        },
        {
          "type": "listItem",
          "content": [
            {
              "type": "paragraph",
              "content": [
                {
                  "type": "text",
                  "text": "Hirnblutungen"
                }
              ]
            }
          ]
        },
        {
          "type": "listItem",
          "content": [
            {
              "type": "paragraph",
              "content": [
                {
                  "type": "text",
                  "text": "SHT"
                }
              ]
            }
          ]
        }
      ]
    },
    {
      "type": "heading",
      "attrs": {
        "level": 3
      },
      "content": [
        {
          "type": "text",
          "text": "Metamorphopsie (Dysmorphopsie)"
        }
      ]
    },
    {
      "type": "bulletList",
      "content": [
        {
          "type": "listItem",
          "content": [
            {
              "type": "paragraph",
              "content": [
                {
                  "type": "text",
                  "text": "Gegenstände oder Lebewesen der Umgebung werden als in Form und Farbe verändert/verzerrt wahrgenommen "
                }
              ]
            }
          ]
        },
        {
          "type": "listItem",
          "content": [
            {
              "type": "paragraph",
              "content": [
                {
                  "type": "text",
                  "text": "Z.B. ein normal gebauter Mann wird mit riesig langen Beinen wahrgenommen "
                }
              ]
            }
          ]
        }
      ]
    },
    {
      "type": "paragraph",
      "content": [
        {
          "type": "text",
          "text": "Bei"
        }
      ]
    },
    {
      "type": "bulletList",
      "content": [
        {
          "type": "listItem",
          "content": [
            {
              "type": "paragraph",
              "content": [
                {
                  "type": "text",
                  "text": "Augenerkrankungen"
                }
              ]
            }
          ]
        },
        {
          "type": "listItem",
          "content": [
            {
              "type": "paragraph",
              "content": [
                {
                  "type": "text",
                  "text": "Sehnervbeschädigung"
                }
              ]
            }
          ]
        },
        {
          "type": "listItem",
          "content": [
            {
              "type": "paragraph",
              "content": [
                {
                  "type": "text",
                  "text": "Entzündliche Veränderungen im Sehzentrum"
                }
              ]
            }
          ]
        },
        {
          "type": "listItem",
          "content": [
            {
              "type": "paragraph",
              "content": [
                {
                  "type": "text",
                  "text": "Schlaganfälle"
                }
              ]
            }
          ]
        },
        {
          "type": "listItem",
          "content": [
            {
              "type": "paragraph",
              "content": [
                {
                  "type": "text",
                  "text": "Hirnblutungen"
                }
              ]
            }
          ]
        },
        {
          "type": "listItem",
          "content": [
            {
              "type": "paragraph",
              "content": [
                {
                  "type": "text",
                  "text": "SHT"
                }
              ]
            }
          ]
        },
        {
          "type": "listItem",
          "content": [
            {
              "type": "paragraph",
              "content": [
                {
                  "type": "text",
                  "text": "Derealisation"
                }
              ]
            }
          ]
        }
      ]
    },
    {
      "type": "heading",
      "attrs": {
        "level": 3
      },
      "content": [
        {
          "type": "text",
          "text": "Mikro- / Makropsie"
        }
      ]
    },
    {
      "type": "bulletList",
      "content": [
        {
          "type": "listItem",
          "content": [
            {
              "type": "paragraph",
              "content": [
                {
                  "type": "text",
                  "text": "Gegenstände oder Lebenwesen werden als größer/kleiner wahrgenommen"
                }
              ]
            }
          ]
        },
        {
          "type": "listItem",
          "content": [
            {
              "type": "paragraph",
              "content": [
                {
                  "type": "text",
                  "text": "z.B. Eine Maus wird so groß wie ein Hund gesehen"
                }
              ]
            }
          ]
        }
      ]
    },
    {
      "type": "paragraph",
      "content": [
        {
          "type": "text",
          "text": "Bei"
        }
      ]
    },
    {
      "type": "bulletList",
      "content": [
        {
          "type": "listItem",
          "content": [
            {
              "type": "paragraph",
              "content": [
                {
                  "type": "text",
                  "text": "Entzugsdelier"
                }
              ]
            }
          ]
        },
        {
          "type": "listItem",
          "content": [
            {
              "type": "paragraph",
              "content": [
                {
                  "type": "text",
                  "text": "Migräne"
                }
              ]
            }
          ]
        },
        {
          "type": "listItem",
          "content": [
            {
              "type": "paragraph",
              "content": [
                {
                  "type": "text",
                  "text": "Epilepsie"
                }
              ]
            }
          ]
        },
        {
          "type": "listItem",
          "content": [
            {
              "type": "paragraph",
              "content": [
                {
                  "type": "text",
                  "text": "Kelinkindern"
                }
              ]
            }
          ]
        },
        {
          "type": "listItem",
          "content": [
            {
              "type": "paragraph",
              "content": [
                {
                  "type": "text",
                  "text": "Virusinfektionen (Epstein-Barr-Virus)"
                }
              ]
            }
          ]
        },
        {
          "type": "listItem",
          "content": [
            {
              "type": "paragraph",
              "content": [
                {
                  "type": "text",
                  "text": "Drogenmissbrauch"
                }
              ]
            }
          ]
        }
      ]
    },
    {
      "type": "heading",
      "attrs": {
        "level": 2
      },
      "content": [
        {
          "type": "text",
          "text": "Differntialdiagnose"
        }
      ]
    },
    {
      "type": "bulletList",
      "content": [
        {
          "type": "listItem",
          "content": [
            {
              "type": "paragraph",
              "content": [
                {
                  "type": "text",
                  "text": "Wahnwahrnehmung: Gegenstand wird richtig erkannt, aber Wahnhaft umgedeutet."
                },
                {
                  "type": "hardBreak"
                },
                {
                  "type": "text",
                  "text": "Illusion: Gegenstand selbst wird verkannt."
                }
              ]
            }
          ]
        },
        {
          "type": "listItem",
          "content": [
            {
              "type": "paragraph",
              "content": [
                {
                  "type": "text",
                  "text": "Halluzination: Keine realen Sinneseindrücke"
                },
                {
                  "type": "hardBreak"
                },
                {
                  "type": "text",
                  "text": "Illusion: Reale Sinneseindrücke"
                }
              ]
            }
          ]
        }
      ]
    },
    {
      "type": "paragraph",
      "content": [
        {
          "type": "text",
          "text": "Beispiel"
        }
      ]
    },
    {
      "type": "bulletList",
      "content": [
        {
          "type": "listItem",
          "content": [
            {
              "type": "paragraph",
              "content": [
                {
                  "type": "text",
                  "text": "Kind sieht Vorhang UND Gestalt darin (Pareidolie)"
                }
              ]
            }
          ]
        },
        {
          "type": "listItem",
          "content": [
            {
              "type": "paragraph",
              "content": [
                {
                  "type": "text",
                  "text": "Dann glaubt es, dort eine Gestalt zu sehen, nimmt den Vorhang  nichtmehr als solchen wahr (Illusion)"
                }
              ]
            }
          ]
        },
        {
          "type": "listItem",
          "content": [
            {
              "type": "paragraph",
              "content": [
                {
                  "type": "text",
                  "text": "Kind ist sich gewiss, dass eine weiße Gestalt nach ihm greift (Halluzination)"
                }
              ]
            }
          ]
        }
      ]
    },
    {
      "type": "paragraph"
    }
  ]
}